random_sort/__init__.py
random_sort/random_sort.py
random_sort-0.1.1.dist-info/LICENSE
random_sort-0.1.1.dist-info/METADATA
random_sort-0.1.1.dist-info/WHEEL
random_sort-0.1.1.dist-info/top_level.txt
random_sort-0.1.1.dist-info/RECORD
