Metadata-Version: 2.1
Name: random_sort
Version: 0.1.1
Summary: A Python library that implements a sort algorithm based on randomization
Home-page: https://github.com/FrancescoGrazioso/random_sort
Author: Your Name
Author-email: your.email@example.com
License: UNKNOWN
Project-URL: Bug Tracker, https://github.com/FrancescoGrazioso/random_sort/issues
Project-URL: Documentation, https://github.com/FrancescoGrazioso/random_sort
Project-URL: Source Code, https://github.com/FrancescoGrazioso/random_sort
Keywords: sort,random,bogosort,algorithm,humor
Platform: UNKNOWN
Classifier: Programming Language :: Python :: 3
Classifier: License :: OSI Approved :: MIT License
Classifier: Operating System :: OS Independent
Classifier: Development Status :: 4 - Beta
Classifier: Intended Audience :: Developers
Classifier: Intended Audience :: Education
Classifier: Topic :: Software Development :: Libraries
Classifier: Topic :: Software Development :: Libraries :: Python Modules
Requires-Python: >=3.6
License-File: LICENSE
